{
  "isSample": false,
  "generatedAt": "2026-06-22T14:34:57.813Z",
  "competition": {
    "name": "FIFA World Cup 2026",
    "startDate": "2026-06-11"
  },
  "challenge": {
    "title": "UM GOLO · UM KM",
    "kmPerGoal": 1
  },
  "goals": {
    "total": 121,
    "matchesPlayed": 40,
    "firstGoalDate": "2026-06-11T19:00Z"
  },
  "runners": [
    {
      "id": "jose",
      "name": "José",
      "km": 33.11,
      "required": 121,
      "remaining": 87.89,
      "progress": 0.2736363636363636,
      "status": "ok",
      "stats": {
        "longestRun": 12.06,
        "runStreak": 2,
        "restStreak": 4
      },
      "runs": [
        {
          "date": "2026-06-21",
          "km": 12.06
        },
        {
          "date": "2026-06-16",
          "km": 7.05
        },
        {
          "date": "2026-06-14",
          "km": 10
        },
        {
          "date": "2026-06-13",
          "km": 4
        }
      ]
    },
    {
      "id": "daniel",
      "name": "Tiago",
      "km": 41.7,
      "required": 121,
      "remaining": 79.3,
      "progress": 0.34462809917355375,
      "status": "ok",
      "stats": {
        "longestRun": 11.8,
        "runStreak": 3,
        "restStreak": 3
      },
      "runs": [
        {
          "date": "2026-06-20",
          "km": 8.2
        },
        {
          "date": "2026-06-18",
          "km": 11.8
        },
        {
          "date": "2026-06-16",
          "km": 5.9
        },
        {
          "date": "2026-06-15",
          "km": 5.8
        },
        {
          "date": "2026-06-14",
          "km": 10
        }
      ]
    }
  ],
  "errors": []
}
