{
  "isSample": false,
  "generatedAt": "2026-06-16T08:25:35.764Z",
  "competition": {
    "name": "FIFA World Cup 2026",
    "startDate": "2026-06-11"
  },
  "challenge": {
    "title": "UM GOLO · UM KM",
    "kmPerGoal": 1
  },
  "goals": {
    "total": 46,
    "matchesPlayed": 16,
    "firstGoalDate": "2026-06-11T19:00Z"
  },
  "runners": [
    {
      "id": "jose",
      "name": "José",
      "km": 14,
      "required": 46,
      "remaining": 32,
      "progress": 0.30434782608695654,
      "status": "ok",
      "stats": {
        "longestRun": 10,
        "runStreak": 2,
        "restStreak": 2
      },
      "runs": [
        {
          "date": "2026-06-14",
          "km": 10
        },
        {
          "date": "2026-06-13",
          "km": 4
        }
      ]
    },
    {
      "id": "daniel",
      "name": "Tiago",
      "km": 15.8,
      "required": 46,
      "remaining": 30.2,
      "progress": 0.34347826086956523,
      "status": "ok",
      "stats": {
        "longestRun": 10,
        "runStreak": 2,
        "restStreak": 3
      },
      "runs": [
        {
          "date": "2026-06-15",
          "km": 5.8
        },
        {
          "date": "2026-06-14",
          "km": 10
        }
      ]
    }
  ],
  "errors": []
}
